[
  { "id": 1, "german": "Das Zimmer", "english": "room" },
  { "id": 2, "german": "Die Wohnung", "english": "apartment" },
  { "id": 3, "german": "Der Arbeitsraum", "english": "work room" },
  { "id": 4, "german": "Die Möbel", "english": "furniture" },
  { "id": 5, "german": "Das Badezimmer", "english": "bathroom" },
  { "id": 6, "german": "Der Tisch", "english": "table" },
  { "id": 7, "german": "Das Schlafzimmer", "english": "bedroom" },
  { "id": 8, "german": "Der Schreibtisch", "english": "desk" },
  { "id": 9, "german": "Das Wohnzimmer", "english": "living room" },
  { "id": 10, "german": "Die Schreibwaren", "english": "stationery" },
  { "id": 11, "german": "Das Kinderzimmer", "english": "children's room" },
  { "id": 12, "german": "Der Sessel", "english": "armchair" },
  { "id": 13, "german": "Die Toilette", "english": "toilet" },
  { "id": 14, "german": "Das Sofa", "english": "sofa" },
  { "id": 15, "german": "Der Balkon", "english": "balcony" },
  { "id": 16, "german": "Der Stuhl", "english": "chair" },
  { "id": 17, "german": "Die Küche", "english": "kitchen" },
  { "id": 18, "german": "Der Teppich", "english": "carpet" },
  { "id": 19, "german": "Das Gerät", "english": "equipment" },
  { "id": 20, "german": "Das Bett", "english": "bed" },
  { "id": 21, "german": "Der Herd", "english": "stove" },
  { "id": 22, "german": "Das Geschoss", "english": "floor / level" },
  { "id": 23, "german": "Die Waschmaschine", "english": "washing machine" },
  { "id": 24, "german": "Die Etage", "english": "floor / level" },
  { "id": 25, "german": "Der Fernseher", "english": "TV" },
  { "id": 26, "german": "Der Stock", "english": "floor / level" },
  { "id": 27, "german": "Der Drucker", "english": "printer" },
  { "id": 28, "german": "Das Untergeschoss", "english": "basement" },
  { "id": 29, "german": "Das Telefon", "english": "telephone" },
  { "id": 30, "german": "Das Erdgeschoss", "english": "ground floor" },
  { "id": 31, "german": "Die Lampe", "english": "lamp" },
  { "id": 32, "german": "Der Boden", "english": "floor surface" },
  { "id": 33, "german": "Das Waschbecken", "english": "washbasin" },
  { "id": 34, "german": "Der Flur", "english": "hallway" },
  { "id": 35, "german": "Der Kühlschrank", "english": "fridge" },
  { "id": 36, "german": "Der Garten", "english": "garden" },
  { "id": 37, "german": "Der Schrank", "english": "cupboard" },
  { "id": 38, "german": "Die Farbe", "english": "colour" },
  { "id": 39, "german": "Das Regal", "english": "shelf" },
  { "id": 40, "german": "Die Treppe", "english": "staircase" },
  { "id": 41, "german": "Das Material", "english": "material" },
  { "id": 42, "german": "Die Rolltreppe", "english": "escalator" },
  { "id": 43, "german": "Der Vertrag", "english": "contract" },
  { "id": 44, "german": "Der Aufzug", "english": "elevator" },
  { "id": 45, "german": "Die Miete", "english": "rent" },
  { "id": 46, "german": "Die Zeitschrift", "english": "magazine" },
  { "id": 47, "german": "Der Nachbar", "english": "neighbour" },
  { "id": 48, "german": "Die Zeitung", "english": "newspaper" },
  { "id": 49, "german": "Das Dach", "english": "roof" },
  { "id": 50, "german": "Der Schornstein", "english": "chimney" },

  { "id": 51, "german": "Der Raum", "english": "space / room" },
  { "id": 52, "german": "Der Schlüssel", "english": "key" },
  { "id": 53, "german": "Das Fenster", "english": "window" },
  { "id": 54, "german": "Die Tür", "english": "door" },
  { "id": 55, "german": "Der Baum", "english": "tree" },
  { "id": 56, "german": "Der Spiegel", "english": "mirror" },
  { "id": 57, "german": "Das Bild", "english": "picture" },
  { "id": 58, "german": "Die Blume", "english": "flower" },
  { "id": 59, "german": "Das Einzelzimmer", "english": "single room" },
  { "id": 60, "german": "Das Doppelzimmer", "english": "double room" },
  { "id": 61, "german": "Das Feuer", "english": "fire" },
  { "id": 62, "german": "Die Wand", "english": "wall" },

  { "id": 63, "german": "grün", "english": "green" },
  { "id": 64, "german": "schwarz", "english": "black" },
  { "id": 65, "german": "weiß", "english": "white" },
  { "id": 66, "german": "grau", "english": "grey" },
  { "id": 67, "german": "rot", "english": "red" },
  { "id": 68, "german": "blau", "english": "blue" },
  { "id": 69, "german": "gelb", "english": "yellow" }
]